msvc_runtime.cp310-win_amd64.pyd
msvc_runtime-14.42.34433.data/data/concrt140.dll
msvc_runtime-14.42.34433.data/data/msvcp140.dll
msvc_runtime-14.42.34433.data/data/msvcp140_1.dll
msvc_runtime-14.42.34433.data/data/msvcp140_2.dll
msvc_runtime-14.42.34433.data/data/msvcp140_atomic_wait.dll
msvc_runtime-14.42.34433.data/data/msvcp140_codecvt_ids.dll
msvc_runtime-14.42.34433.data/data/vcamp140.dll
msvc_runtime-14.42.34433.data/data/vccorlib140.dll
msvc_runtime-14.42.34433.data/data/vcomp140.dll
msvc_runtime-14.42.34433.data/data/vcruntime140_threads.dll
msvc_runtime-14.42.34433.data/data/Scripts/concrt140.dll
msvc_runtime-14.42.34433.data/data/Scripts/msvcp140.dll
msvc_runtime-14.42.34433.data/data/Scripts/msvcp140_1.dll
msvc_runtime-14.42.34433.data/data/Scripts/msvcp140_2.dll
msvc_runtime-14.42.34433.data/data/Scripts/msvcp140_atomic_wait.dll
msvc_runtime-14.42.34433.data/data/Scripts/msvcp140_codecvt_ids.dll
msvc_runtime-14.42.34433.data/data/Scripts/vcamp140.dll
msvc_runtime-14.42.34433.data/data/Scripts/vccorlib140.dll
msvc_runtime-14.42.34433.data/data/Scripts/vcomp140.dll
msvc_runtime-14.42.34433.data/data/Scripts/vcruntime140.dll
msvc_runtime-14.42.34433.data/data/Scripts/vcruntime140_1.dll
msvc_runtime-14.42.34433.data/data/Scripts/vcruntime140_threads.dll
msvc_runtime-14.42.34433.dist-info/LICENSE
msvc_runtime-14.42.34433.dist-info/METADATA
msvc_runtime-14.42.34433.dist-info/WHEEL
msvc_runtime-14.42.34433.dist-info/top_level.txt
msvc_runtime-14.42.34433.dist-info/RECORD
