Metadata-Version: 2.1
Name: msvc_runtime
Version: 14.42.34433
Summary: Install the Microsoft™ Visual C++™ runtime DLLs to the sys.prefix and Scripts directories
License: Proprietary
Platform: Windows
Classifier: Development Status :: 5 - Production/Stable
Classifier: License :: Other/Proprietary License
Classifier: Operating System :: Microsoft :: Windows
Classifier: Programming Language :: C++
Requires-Python: >=3.5
License-File: LICENSE
